faker_enum/__init__.py
faker_enum-0.0.2.dist-info/LICENSE
faker_enum-0.0.2.dist-info/METADATA
faker_enum-0.0.2.dist-info/WHEEL
faker_enum-0.0.2.dist-info/top_level.txt
faker_enum-0.0.2.dist-info/zip-safe
faker_enum-0.0.2.dist-info/RECORD
