Metadata-Version: 2.1
Name: faker-enum
Version: 0.0.2
Summary: Enum provider for the Faker Python package.
Home-page: https://github.com/NazarioJL/faker_enum
Author: NazarioJL
Author-email: jlnazario@hotmail.com
License: MIT License
Keywords: faker enum test data
Platform: any
Classifier: Development Status :: 3 - Alpha
Classifier: Environment :: Console
Classifier: Intended Audience :: Developers
Classifier: License :: OSI Approved :: MIT License
Classifier: Operating System :: OS Independent
Classifier: Programming Language :: Python
Classifier: Programming Language :: Python :: 3.6
Classifier: Programming Language :: Python :: 3.7
Classifier: Programming Language :: Python :: Implementation :: PyPy
Classifier: Topic :: Software Development :: Libraries :: Python Modules
Classifier: Topic :: Software Development :: Testing
Classifier: Topic :: Utilities
Requires-Dist: faker
